{
  "slug": "adaptation-vs",
  "topic": "adaptation vs",
  "title": "What is Adaptation Vs?",
  "category": "science",
  "content": "Adaptation refers to the process by which living organisms, including humans, adjust to their environment in order to survive and thrive.\n\nThe concept of adaptation is central to understanding how living things interact with their surroundings. All living organisms, from plants and animals to humans, have an inherent ability to adapt to their environment. This ability is essential for survival, as it allows organisms to respond to changes in their surroundings and make the necessary adjustments to stay alive. Adaptation can occur in various forms, such as physical changes, behavioral modifications, or physiological responses.\n\nOne of the key aspects of adaptation is its ability to occur over different time scales. Some adaptations can occur rapidly, such as the ability of the human body to adjust to changes in temperature or altitude. Other adaptations, however, may take longer to develop, such as the evolution of new physical traits over many generations. Additionally, adaptation is not limited to individual organisms, but can also occur at the level of populations or entire species. For example, a population of animals may adapt to a new predator by developing new defense mechanisms or changing their behavior to avoid the predator.\n\nThe process of adaptation is complex and involves many different factors, including genetic variation, environmental pressures, and the interactions between organisms and their environment. Genetic variation provides the raw material for adaptation, as it allows organisms to express different traits and characteristics. Environmental pressures, such as changes in climate or the presence of predators, then act on this variation, favoring the survival and reproduction of organisms with traits that are better suited to the environment. Over time, this process of natural selection can lead to the evolution of new adaptations, allowing organisms to better fit their environment and increase their chances of survival.\n\nThe main components of adaptation include:\n* Genetic variation, which provides the raw material for adaptation\n* Environmental pressures, such as changes in climate or the presence of predators\n* Natural selection, which acts on genetic variation to favor the survival and reproduction of organisms with advantageous traits\n* Physiological responses, such as changes in heart rate or blood pressure, which allow organisms to respond to immediate environmental challenges\n* Behavioral modifications, such as changes in foraging behavior or social interactions, which can help organisms adapt to their environment\n* Evolutionary changes, which occur over many generations and can result in the development of new physical traits or characteristics\n\nDespite its importance, adaptation is often misunderstood. Some common misconceptions about adaptation include:\n* The idea that adaptation is a deliberate or conscious process, when in fact it is often an unconscious response to environmental pressures\n* The notion that adaptation always involves the development of new physical traits, when in fact it can also involve behavioral or physiological changes\n* The assumption that adaptation is always a positive process, when in fact it can also involve trade-offs or compromises, such as the loss of one trait in order to gain another\n* The belief that adaptation is unique to living organisms, when in fact it can also occur in non-living systems, such as the adaptation of a machine to its environment\n\nA real-world example of adaptation can be seen in the case of high-altitude climbers. When humans ascend to high altitudes, their bodies must adapt to the lower oxygen levels in the air. One of the ways the body adapts is by increasing the production of red blood cells, which carry oxygen to the body's tissues. This adaptation allows the body to compensate for the lower oxygen levels and maintain its normal functions, even in the challenging environment of high altitude.\n\nIn summary, adaptation refers to the process by which living organisms adjust to their environment in order to survive and thrive, involving a complex interplay of genetic variation, environmental pressures, and physiological and behavioral responses.",
  "meta_description": "A clear, simple explanation of adaptation vs - definition, key concepts, examples, and common misconceptions.",
  "word_count": 644,
  "generated_date": "2026-02-06T16:36:56.047671"
}