{
  "slug": "common-misconceptions-about-precipitation",
  "topic": "common misconceptions about precipitation",
  "title": "What is Common Misconceptions About Precipitation?",
  "category": "science",
  "content": "1. INTRODUCTION:\nPrecipitation is a fundamental aspect of the Earth's water cycle, playing a crucial role in shaping our environment and influencing various aspects of our lives. Despite its importance, misconceptions about precipitation are common due to the complexity of the processes involved and the limited understanding of the underlying mechanisms. These misconceptions often arise from oversimplification, misinformation, or a lack of exposure to accurate information. Understanding the correct concepts and mechanisms of precipitation is essential to appreciate its significance and impact on our planet.\n\n2. MISCONCEPTION LIST:\nThe following are some common misconceptions about precipitation, along with the reality and the reasons behind these misconceptions:\n- Myth: Rain occurs when the air reaches a certain temperature.\n  Reality: Rain occurs when the air reaches its dew point, which is the temperature at which the air becomes saturated with water vapor and can no longer hold all the moisture, causing the water vapor to condense into droplets.\n  Why people believe this: The concept of dew point is often misunderstood, and people tend to associate rain with temperature rather than the air's capacity to hold moisture.\n- Myth: All clouds produce precipitation.\n  Reality: Not all clouds produce precipitation. While clouds are formed when water vapor condenses into visible liquid droplets or ice crystals, precipitation occurs only when these droplets or crystals become too heavy to remain suspended in the air.\n  Why people believe this: The association of clouds with rain or snow leads people to assume that all clouds produce precipitation, overlooking the fact that clouds can exist without producing any precipitation.\n- Myth: The water that evaporates from the ocean is the same water that falls as precipitation.\n  Reality: While a significant portion of the water that evaporates from the ocean does fall as precipitation, some of it is lost to other processes, such as being stored in glaciers or groundwater.\n  Why people believe this: The water cycle is often oversimplified, leading to the assumption that water evaporates from the ocean and directly falls as precipitation, without considering the other paths it can take.\n- Myth: Heavy precipitation is always associated with severe thunderstorms.\n  Reality: Heavy precipitation can occur with or without thunderstorms. Other weather systems, such as frontal systems or tropical cyclones, can also produce heavy precipitation.\n  Why people believe this: The dramatic nature of thunderstorms and the heavy precipitation that often accompanies them can lead to the assumption that all heavy precipitation is associated with severe weather.\n- Myth: Precipitation always falls in a uniform pattern.\n  Reality: Precipitation patterns can vary greatly, with some areas receiving much more precipitation than others due to factors such as topography, wind direction, and the movement of weather systems.\n  Why people believe this: The idea of uniform precipitation patterns may arise from simplified representations of weather systems, which do not account for the complex interactions between atmospheric and geographical factors.\n- Myth: The amount of precipitation an area receives is directly related to its distance from the ocean.\n  Reality: While distance from the ocean can influence the amount of precipitation an area receives, other factors such as topography, prevailing wind direction, and the movement of weather systems play a much more significant role.\n  Why people believe this: The assumption that distance from the ocean is the primary factor in determining precipitation may stem from the fact that coastal areas often receive more precipitation than inland areas, but it overlooks the complexity of the factors involved.\n\n3. HOW TO REMEMBER:\nTo avoid these misconceptions, it is essential to understand the basic principles of the water cycle and the processes that govern precipitation. This can be achieved by:\n- Familiarizing yourself with the concept of dew point and its role in precipitation\n- Recognizing that not all clouds produce precipitation and that precipitation requires specific conditions\n- Understanding the various paths that water can take in the water cycle\n- Being aware of the different weather systems that can produce heavy precipitation\n- Appreciating the complexity of precipitation patterns and the factors that influence them\n\n4. SUMMARY:\nThe key to avoiding misconceptions about precipitation is to remember that precipitation is a complex process influenced by multiple factors, including the air's capacity to hold moisture, the type of clouds present, and the movement of weather systems. By understanding these factors and recognizing the complexity of the water cycle, you can gain a more accurate appreciation of the mechanisms that govern precipitation and avoid common misconceptions.",
  "meta_description": "A clear, simple explanation of common misconceptions about precipitation - definition, key concepts, examples, and common misconceptions.",
  "word_count": 739,
  "generated_date": "2026-02-06T16:41:33.739828"
}