{
  "slug": "what-affects-gross-domestic-product",
  "topic": "what affects gross domestic product",
  "title": "What Affects Gross Domestic Product",
  "category": "economics",
  "content": "1. INTRODUCTION:\nGross domestic product (GDP) is the total value of goods and services produced within a country's borders. Understanding the factors that affect GDP is crucial because it helps policymakers, businesses, and individuals make informed decisions about investments, resource allocation, and economic development. GDP is a key indicator of a country's economic health, and knowing what influences it can help identify areas for improvement and opportunities for growth.\n\n2. MAIN FACTORS:\nThe following factors affect GDP:\n- Consumer Spending: When consumers spend more on goods and services, it increases the demand for products, leading to higher production levels and, consequently, a higher GDP. The effect of consumer spending on GDP is positive.\n- Investment: Investment in capital goods, such as new equipment and buildings, increases the production capacity of businesses, leading to higher GDP. The effect of investment on GDP is positive.\n- Government Spending: Government expenditures on goods and services, infrastructure, and social programs can stimulate economic activity, increasing GDP. However, excessive government spending can lead to inflation and decreased economic efficiency, making the effect variable.\n- Net Exports: When a country exports more goods and services than it imports, it increases the demand for domestic products, leading to higher GDP. The effect of net exports on GDP is positive.\n- Technology: Advances in technology can increase productivity, allowing businesses to produce more goods and services with the same amount of resources, leading to higher GDP. The effect of technology on GDP is positive.\n- Labor Force: A growing and skilled labor force can increase productivity and economic output, leading to higher GDP. The effect of labor force on GDP is positive.\n- Natural Resources: The availability and quality of natural resources, such as oil, gas, and minerals, can affect the production costs and capacity of businesses, influencing GDP. The effect of natural resources on GDP is variable, depending on the type and abundance of resources.\n\n3. INTERCONNECTIONS:\nThese factors are interconnected and can influence each other. For example, an increase in consumer spending can lead to higher demand for goods and services, which can stimulate investment in new production capacity. Similarly, advances in technology can increase productivity, leading to higher economic output and, consequently, higher GDP. Government spending can also influence consumer spending and investment by providing infrastructure and social programs that support economic activity. The labor force and natural resources can also interact, as the availability of skilled workers can affect the extraction and processing of natural resources.\n\n4. CONTROLLABLE VS UNCONTROLLABLE:\nSome factors that affect GDP can be managed, while others are outside of human control. Government spending, investment, and consumer spending are, to some extent, controllable, as policymakers and businesses can implement policies and strategies to influence these factors. Technology and labor force growth can also be influenced through education, research, and training programs. However, natural resources and global economic conditions are largely uncontrollable, as they depend on geological and geographical factors, as well as global market trends.\n\n5. SUMMARY:\nThe most important factors to understand when it comes to GDP are consumer spending, investment, government spending, and labor force growth. These factors are interconnected and can influence each other, and understanding their relationships is crucial for making informed decisions about economic development and resource allocation. By recognizing the causes and effects of these factors, policymakers, businesses, and individuals can work together to create an environment that supports economic growth and prosperity. Additionally, being aware of the controllable and uncontrollable factors can help stakeholders develop strategies to mitigate risks and capitalize on opportunities, ultimately contributing to a healthier and more stable economy.",
  "meta_description": "A clear, simple explanation of what affects gross domestic product - definition, key concepts, examples, and common misconceptions.",
  "word_count": 598,
  "generated_date": "2026-02-06T17:59:12.575444",
  "angle": "what-affects-it",
  "base_concept": "gross-domestic-product"
}