{
  "slug": "types-of-chronic-pain",
  "topic": "Types of Chronic Pain",
  "base_concept": "chronic pain",
  "angle": "types-of",
  "title": "Types of Chronic Pain",
  "category": "health",
  "content": "There are four main categories of chronic pain, organized by their underlying causes and mechanisms: **Nociceptive Pain**, **Neuropathic Pain**, **Psychogenic Pain**, and **Idiopathic Pain**.\n\n## Main Categories\n- **Nociceptive Pain** \u2014 pain caused by tissue damage or inflammation, characterized by a clear source of pain and a direct relationship between the pain and the underlying condition, as seen in **Rheumatoid Arthritis**, a chronic inflammatory disorder that causes pain and stiffness in the joints.\n- **Neuropathic Pain** \u2014 pain caused by damage to the nervous system, characterized by shooting, burning, or stabbing pain, often without a clear source, as seen in **Diabetic Neuropathy**, a complication of diabetes that damages the nerves and causes chronic pain.\n- **Psychogenic Pain** \u2014 pain caused by psychological factors, characterized by a lack of clear physical cause and a strong emotional component, as seen in **Somatization Disorder**, a condition in which a person experiences chronic pain and other physical symptoms without a clear medical cause.\n- **Idiopathic Pain** \u2014 pain without a clear cause or explanation, characterized by a lack of underlying condition or mechanism, as seen in **Fibromyalgia**, a chronic condition characterized by widespread muscle pain and fatigue without a clear cause.\n\n## Comparison Table\n| Category | Cause | Mechanism | Example |\n| --- | --- | --- | --- |\n| **Nociceptive Pain** | Tissue damage or inflammation | Activation of nociceptors | **Rheumatoid Arthritis** |\n| **Neuropathic Pain** | Damage to the nervous system | Abnormal nerve signaling | **Diabetic Neuropathy** |\n| **Psychogenic Pain** | Psychological factors | Emotional and cognitive processes | **Somatization Disorder** |\n| **Idiopathic Pain** | Unknown | Unknown | **Fibromyalgia** |\n\n## How They Relate\nThe categories of chronic pain often overlap and can be difficult to distinguish, particularly between **Nociceptive Pain** and **Neuropathic Pain**, as conditions like **Rheumatoid Arthritis** can cause both tissue damage and nerve damage. Additionally, **Psychogenic Pain** can be confused with **Idiopathic Pain**, as the lack of clear physical cause can make it difficult to determine whether the pain is caused by psychological factors or an unknown mechanism. For example, a person with **Somatization Disorder** may experience chronic pain that is similar to **Fibromyalgia**, but with a clear psychological component. Understanding the relationships between these categories is essential for developing effective treatment plans and improving patient outcomes. \n- **Nociceptive Pain** and **Neuropathic Pain** often co-occur in conditions like **Complex Regional Pain Syndrome**, which is characterized by chronic pain and inflammation after an injury.\n- **Psychogenic Pain** can be a component of **Idiopathic Pain** conditions like **Fibromyalgia**, where psychological factors can contribute to the experience of chronic pain.\n- **Idiopathic Pain** conditions like **Fibromyalgia** can be difficult to distinguish from **Psychogenic Pain** conditions like **Somatization Disorder**, highlighting the need for comprehensive assessment and diagnosis.",
  "meta_description": "A clear, simple explanation of Types of Chronic Pain - definition, key concepts, examples, and common misconceptions.",
  "word_count": 462,
  "generated_date": "2026-02-16T20:46:46.117074"
}