{
  "slug": "stages-of-roth-ira",
  "topic": "stages of roth ira",
  "title": "What is Stages Of Roth Ira?",
  "category": "finance",
  "content": "1. INTRODUCTION:\nThe stages of a Roth Individual Retirement Account (Roth IRA) refer to the different phases that an account goes through from its inception to its eventual distribution. Understanding these stages is crucial for effective retirement planning, as it helps individuals make informed decisions about their investments and ensure that they are making the most of their savings. Classification of these stages matters because it allows individuals to identify where they are in the process, anticipate what comes next, and take the necessary steps to achieve their retirement goals.\n\n2. MAIN CATEGORIES:\nThe stages of a Roth IRA can be broadly categorized into the following:\n- **Contribution Stage**: This stage involves making contributions to the Roth IRA, which are made with after-tax dollars. Key characteristics of this stage include annual contribution limits and the ability to contribute at any age. For example, an individual may contribute $6,000 to their Roth IRA each year, taking advantage of the tax benefits and potential for long-term growth.\n- **Accumulation Stage**: During this stage, the contributions made to the Roth IRA grow and accumulate over time, potentially earning interest and investment returns. Key characteristics include the potential for tax-free growth and the ability to invest in a variety of assets. For instance, an individual may invest their Roth IRA contributions in a mix of stocks and bonds, watching their account balance grow over the years.\n- **Distribution Stage**: This stage involves withdrawing funds from the Roth IRA, which can be done tax-free and penalty-free if certain conditions are met. Key characteristics include the requirement that the account must be at least five years old and that the individual must be 59 1/2 or older. For example, an individual may withdraw $10,000 from their Roth IRA to supplement their retirement income, without having to pay taxes or penalties.\n- **Inheritance Stage**: This stage occurs when the Roth IRA is passed on to beneficiaries after the account owner's death. Key characteristics include the potential for tax-free growth and the requirement that beneficiaries must take required minimum distributions (RMDs) within a certain timeframe. For instance, an individual may name their spouse as the beneficiary of their Roth IRA, ensuring that the account continues to grow and provide income after their passing.\n\n3. COMPARISON TABLE:\nThe following table summarizes the key differences between the stages of a Roth IRA:\n| Stage | Key Characteristics | Tax Implications | Eligibility Requirements |\n| --- | --- | --- | --- |\n| Contribution | Annual contribution limits, after-tax dollars | Contributions are made with after-tax dollars | Anyone with earned income can contribute |\n| Accumulation | Tax-free growth, investment returns | Earnings grow tax-free | Account must be open and funded |\n| Distribution | Tax-free and penalty-free withdrawals, five-year rule | Withdrawals are tax-free and penalty-free if conditions are met | Account must be at least five years old, individual must be 59 1/2 or older |\n| Inheritance | Tax-free growth, RMDs for beneficiaries | Beneficiaries may be subject to taxes on distributions | Account owner must pass away, beneficiaries must take RMDs |\n\n4. HOW THEY RELATE:\nThe stages of a Roth IRA are interconnected and sequential, with each stage building on the previous one. The contribution stage sets the foundation for the accumulation stage, which in turn sets the stage for the distribution stage. The inheritance stage is a natural consequence of the account owner's passing, and it involves the transfer of the account to beneficiaries. Understanding how these stages relate to one another is essential for creating a comprehensive retirement plan and ensuring that the Roth IRA is used effectively.\n\n5. SUMMARY:\nThe classification system for the stages of a Roth IRA includes the contribution, accumulation, distribution, and inheritance stages, each with its own unique characteristics and requirements, which together provide a framework for understanding and navigating the different phases of a Roth IRA.",
  "meta_description": "A clear, simple explanation of stages of roth ira - definition, key concepts, examples, and common misconceptions.",
  "word_count": 652,
  "generated_date": "2026-02-06T10:52:09.655251"
}