{
  "slug": "education-funding",
  "topic": "education funding",
  "title": "What Is Education Funding?",
  "category": "life_obligations",
  "content": "Education funding is the process of providing financial resources to support the operation of educational institutions and programs.\n\nEducation funding is essential for the functioning of schools, universities, and other educational institutions. It covers a wide range of expenses, including teacher salaries, facilities maintenance, textbooks, and technology. The sources of education funding can vary, but they typically include government allocations, private donations, and tuition fees. In many countries, education is considered a fundamental right, and governments play a significant role in funding educational institutions.\n\nThe way education funding is allocated and managed can have a significant impact on the quality of education provided. Educational institutions have different funding needs, and the allocation of resources must be carefully planned to ensure that all students have access to quality education. This includes providing resources for special needs students, supporting teacher training and development, and maintaining safe and healthy learning environments. Education funding also involves making decisions about how to prioritize spending, as resources are often limited.\n\nEducation funding is a complex issue, and there are many factors to consider when allocating resources. Educational institutions must balance competing demands, such as the need to invest in new technologies, maintain existing facilities, and support student extracurricular activities. Additionally, education funding must be equitable, ensuring that all students have access to similar resources and opportunities, regardless of their background or location.\n\nKey components of education funding include:\n* Government allocations: funding provided by local, state, or national governments to support educational institutions\n* Private donations: contributions from individuals, organizations, or businesses to support specific educational programs or institutions\n* Tuition fees: payments made by students or their families to attend educational institutions\n* Grants: funding provided to support specific educational programs or research projects\n* Endowments: investments made by educational institutions to generate income and support their operations\n* Fundraising: efforts made by educational institutions to raise money from private sources, such as alumni or community events\n\nCommon misconceptions about education funding include:\n* That education funding is only provided by governments, when in fact, private donations and tuition fees also play a significant role\n* That education funding is only used to support teacher salaries, when in fact, it covers a wide range of expenses, including facilities maintenance and technology\n* That education funding is always sufficient, when in fact, many educational institutions face budget constraints and must make difficult decisions about how to allocate limited resources\n* That education funding is only important for wealthy countries, when in fact, education funding is essential for all countries, regardless of their economic development\n\nA real-world example of education funding in action is a local school district that receives government funding to support its operations, but also relies on private donations to fund specific programs, such as music or art classes. The school district must carefully manage its budget to ensure that all students have access to quality education, while also making decisions about how to prioritize spending and allocate resources.\n\nSummary: Education funding is the process of providing financial resources to support the operation of educational institutions and programs, involving a complex interplay of government allocations, private donations, tuition fees, and other sources of revenue.",
  "meta_description": "A clear, simple explanation of education funding - definition, key concepts, examples, and common misconceptions.",
  "word_count": 530,
  "generated_date": "2026-02-06T13:19:23.678619",
  "angle": "what-is",
  "base_concept": "education-funding"
}