{
  "slug": "public-assistance",
  "topic": "public assistance",
  "title": "What Is Public Assistance?",
  "category": "life_obligations",
  "content": "Public assistance is a range of government programs and services designed to provide financial and social support to individuals and families in need. \n\nPublic assistance programs are typically funded by the government and aim to help people who are struggling to meet their basic needs, such as food, shelter, and healthcare. These programs can take many forms, including cash assistance, food stamps, housing subsidies, and job training programs. The goal of public assistance is to provide a safety net for vulnerable populations, such as low-income families, the elderly, and people with disabilities, and to help them become self-sufficient over time.\n\nPublic assistance programs are often administered by government agencies at the local, state, or federal level, and eligibility for these programs is usually based on income, family size, and other factors. For example, a family may be eligible for food stamps if their income is below a certain threshold, while a person with a disability may be eligible for cash assistance to help them pay for basic needs. Public assistance programs can also provide support for education and job training, which can help people gain the skills and knowledge they need to find employment and become self-sufficient.\n\nIn addition to providing financial support, public assistance programs can also provide social support, such as counseling, childcare, and transportation assistance. These services can help people overcome barriers to employment and self-sufficiency, such as lack of childcare or transportation, and can provide a sense of stability and security for families in need. Overall, public assistance programs play a critical role in supporting vulnerable populations and helping them to achieve their full potential.\n\nThe key components of public assistance include:\n* Financial assistance, such as cash benefits or food stamps, to help people meet their basic needs\n* Social services, such as counseling or childcare, to provide support and guidance\n* Job training and education programs, to help people gain the skills and knowledge they need to find employment\n* Housing assistance, such as subsidies or rent assistance, to help people access safe and affordable housing\n* Healthcare services, such as Medicaid or other forms of health insurance, to provide access to medical care\n* Eligibility determination, which involves assessing an individual's or family's income, assets, and other factors to determine their eligibility for public assistance programs\n\nDespite the importance of public assistance, there are many common misconceptions about these programs. For example:\n* Some people believe that public assistance programs are only for people who are lazy or unwilling to work, when in fact most recipients are working or actively seeking employment\n* Others believe that public assistance programs are too generous, when in fact benefits are often limited and subject to strict eligibility requirements\n* Some people assume that public assistance programs are only for certain groups, such as the elderly or people with disabilities, when in fact these programs serve a wide range of populations\n* Others believe that public assistance programs are ineffective, when in fact many programs have been shown to be highly effective in reducing poverty and promoting self-sufficiency\n\nA real-world example of public assistance in action is a single mother who is working part-time and receiving food stamps to help feed her children. She is also enrolled in a job training program to help her gain the skills and education she needs to find a better-paying job and become self-sufficient. With the support of public assistance programs, she is able to provide for her children's basic needs and work towards a brighter future.\n\nIn summary, public assistance is a range of government programs and services designed to provide financial and social support to individuals and families in need, with the ultimate goal of helping them become self-sufficient and achieve their full potential.",
  "meta_description": "A clear, simple explanation of public assistance - definition, key concepts, examples, and common misconceptions.",
  "word_count": 625,
  "generated_date": "2026-02-06T13:02:47.786862",
  "angle": "what-is",
  "base_concept": "public-assistance"
}