{
  "slug": "types-of-loan-interest",
  "topic": "types of loan interest",
  "title": "What is Types Of Loan Interest?",
  "category": "life_obligations",
  "content": "1. INTRODUCTION:\nTypes of loan interest refer to the various methods by which lenders calculate and charge interest on borrowed amounts. Understanding the different types of loan interest is crucial for borrowers to make informed decisions about their loan options, as it can significantly impact the total cost of the loan. Classification of loan interest is essential to help borrowers navigate the complexities of loan agreements and to ensure they are aware of their financial obligations. By categorizing loan interest, individuals can better comprehend the terms and conditions of their loans, making it easier to manage their debt and plan their finances effectively.\n\n2. MAIN CATEGORIES:\n- **Simple Interest**: Simple interest is a type of loan interest where the interest is calculated only on the principal amount borrowed. Key characteristics include a fixed interest rate and interest accrual over time. For example, if an individual borrows $1,000 at a 5% simple interest rate, they will owe $50 in interest after one year, bringing the total amount owed to $1,050.\n- **Compound Interest**: Compound interest is a type of loan interest where the interest is calculated on both the principal amount and any accrued interest. Key characteristics include interest accrual on both principal and interest, and a higher total interest paid over time. For example, if an individual borrows $1,000 at a 5% compound interest rate, they will owe $50 in interest after the first year, but in the second year, they will owe interest on the new principal balance of $1,050, resulting in a higher total interest paid.\n- **Amortized Interest**: Amortized interest is a type of loan interest where the interest is calculated and paid in installments over the life of the loan. Key characteristics include a fixed payment schedule and a decreasing principal balance over time. For example, a mortgage loan with amortized interest may require monthly payments that cover both interest and principal, with the interest portion decreasing as the principal balance decreases.\n- **Fixed-Rate Interest**: Fixed-rate interest is a type of loan interest where the interest rate remains the same over the life of the loan. Key characteristics include a constant interest rate and predictable monthly payments. For example, a personal loan with a fixed interest rate of 6% will have the same interest rate for the entire loan term, making it easier for the borrower to budget and plan their payments.\n- **Variable-Rate Interest**: Variable-rate interest is a type of loan interest where the interest rate can change over the life of the loan. Key characteristics include an adjustable interest rate and potentially changing monthly payments. For example, a credit card with a variable interest rate may have a lower introductory rate that increases after a certain period, resulting in higher interest charges and monthly payments.\n- **Prime Interest**: Prime interest is a type of loan interest where the interest rate is based on the lender's prime rate, which is the rate at which the lender lends to its most creditworthy customers. Key characteristics include a rate that is often lower than other types of interest and is typically reserved for borrowers with excellent credit. For example, a business loan with a prime interest rate may have a lower interest rate than other types of loans, but may require a strong credit history and a solid business plan.\n\n3. COMPARISON TABLE:\n| Type of Interest | Calculation | Key Characteristics | Example |\n| --- | --- | --- | --- |\n| Simple Interest | Interest on principal only | Fixed interest rate, interest accrual over time | $1,000 at 5% = $50 interest after 1 year |\n| Compound Interest | Interest on principal and accrued interest | Interest accrual on both principal and interest, higher total interest | $1,000 at 5% = $50 interest after 1 year, $52.50 after 2 years |\n| Amortized Interest | Interest and principal paid in installments | Fixed payment schedule, decreasing principal balance | Mortgage loan with monthly payments |\n| Fixed-Rate Interest | Constant interest rate | Predictable monthly payments, constant interest rate | Personal loan with 6% fixed interest rate |\n| Variable-Rate Interest | Adjustable interest rate | Potentially changing monthly payments, adjustable interest rate | Credit card with variable interest rate |\n| Prime Interest | Based on lender's prime rate | Lower interest rate, reserved for creditworthy borrowers | Business loan with prime interest rate |\n\n4. HOW THEY RELATE:\nThe different types of loan interest are connected in that they all relate to the calculation and charging of interest on borrowed amounts. However, they differ in their calculation methods, key characteristics, and examples. Simple and compound interest are related in that they both calculate interest on the principal amount, but compound interest also takes into account accrued interest. Amortized interest is related to fixed-rate and variable-rate interest, as it can be used with either type of interest rate. Fixed-rate and variable-rate interest are related in that they both describe the interest rate, but differ in that fixed-rate interest remains constant, while variable-rate interest can change. Prime interest is related to fixed-rate and variable-rate interest, as it is often used as a benchmark for setting interest rates.\n\n5. SUMMARY:\nThe classification system for types of loan interest includes simple interest, compound interest, amortized interest, fixed-rate interest, variable-rate interest, and prime interest, each with its own unique characteristics and calculation methods.",
  "meta_description": "A clear, simple explanation of types of loan interest - definition, key concepts, examples, and common misconceptions.",
  "word_count": 899,
  "generated_date": "2026-02-06T14:27:57.230423"
}