{
  "slug": "what-annual-percentage-rate-depends-on",
  "topic": "what annual percentage rate depends on",
  "title": "What Annual Percentage Rate Depends On",
  "category": "finance",
  "content": "1. INTRODUCTION:\nAnnual percentage rate (APR) is a measure of the total cost of borrowing, including interest rates and fees. Understanding what APR depends on is crucial for making informed decisions about loans, credit cards, and other financial products. The dependencies of APR are the foundation upon which its calculation is based, and they play a significant role in determining the overall cost of borrowing. Without a clear understanding of these dependencies, individuals may find it challenging to navigate the complex world of finance.\n\n2. KEY DEPENDENCIES:\nThe annual percentage rate depends on several key factors, including:\n- The interest rate: This is the basic rate at which interest is calculated on the borrowed amount. It is necessary because it determines the base cost of borrowing. Without an interest rate, it would be impossible to calculate the APR.\n- The compounding frequency: This refers to how often interest is added to the principal amount. It is necessary because it affects the total amount of interest paid over time. Without a compounding frequency, the APR calculation would be incomplete.\n- The loan term: This is the length of time the borrower has to repay the loan. It is necessary because it affects the total amount of interest paid over the life of the loan. Without a loan term, it would be difficult to determine the total cost of borrowing.\n- The fees associated with the loan: These can include origination fees, late payment fees, and other charges. They are necessary because they add to the total cost of borrowing. Without considering fees, the APR calculation would not accurately reflect the true cost of the loan.\n- The principal amount: This is the initial amount borrowed. It is necessary because it serves as the base for calculating interest. Without a principal amount, it would be impossible to calculate the APR.\n\n3. ORDER OF IMPORTANCE:\nWhile all the dependencies are crucial, the interest rate and loan term are the most critical. The interest rate determines the base cost of borrowing, and the loan term affects the total amount of interest paid over time. The compounding frequency and fees associated with the loan are also important, but they have a smaller impact on the overall APR. The principal amount is necessary for calculating the APR, but it is not as critical as the interest rate and loan term.\n\n4. COMMON GAPS:\nOne common gap in understanding APR is assuming that it only depends on the interest rate. However, this is not the case, as the compounding frequency, loan term, fees, and principal amount all play a role in determining the APR. Another common gap is overlooking the fees associated with the loan, which can significantly increase the total cost of borrowing. Additionally, some individuals may assume that the APR is the same as the interest rate, which is not accurate.\n\n5. SUMMARY:\nIn summary, the annual percentage rate depends on a combination of factors, including the interest rate, compounding frequency, loan term, fees, and principal amount. Understanding these dependencies is essential for making informed decisions about loans and credit cards. By recognizing the importance of each dependency and how they interact with one another, individuals can better navigate the complex world of finance and make more informed choices about their financial options. The key to understanding APR is to recognize that it is a comprehensive measure of the total cost of borrowing, and it is only by considering all the relevant dependencies that individuals can truly understand the implications of their financial decisions.",
  "meta_description": "A clear, simple explanation of what annual percentage rate depends on - definition, key concepts, examples, and common misconceptions.",
  "word_count": 589,
  "generated_date": "2026-02-06T11:06:37.830086",
  "angle": "what-it-depends-on",
  "base_concept": "annual-percentage-rate"
}